{
    "type": "FeatureCollection",
    "features": [
        {
            "type": "Feature",
            "geometry": {
                "type": "Polygon",
                "coordinates": [
                    [
                        [
                            99.064538,
                            18.922184,
                            0
                        ],
                        [
                            99.064721,
                            18.921298000000004,
                            0
                        ],
                        [
                            99.064754,
                            18.920601,
                            0
                        ],
                        [
                            99.06480300000001,
                            18.917736,
                            0
                        ],
                        [
                            99.065035,
                            18.915868,
                            0
                        ],
                        [
                            99.065584,
                            18.915995000000002,
                            0
                        ],
                        [
                            99.067563,
                            18.915741,
                            0
                        ],
                        [
                            99.06782900000002,
                            18.915518999999996,
                            0
                        ],
                        [
                            99.069591,
                            18.913618999999997,
                            0
                        ],
                        [
                            99.06987400000001,
                            18.913571,
                            0
                        ],
                        [
                            99.070223,
                            18.913603,
                            0
                        ],
                        [
                            99.072453,
                            18.914773000000004,
                            0
                        ],
                        [
                            99.07360200000001,
                            18.91816,
                            0
                        ],
                        [
                            99.073818,
                            18.918414,
                            0
                        ],
                        [
                            99.07411800000001,
                            18.918603,
                            0
                        ],
                        [
                            99.076596,
                            18.918745,
                            0
                        ],
                        [
                            99.076912,
                            18.918634,
                            0
                        ],
                        [
                            99.077228,
                            18.918381,
                            0
                        ],
                        [
                            99.079605,
                            18.915451,
                            0
                        ],
                        [
                            99.085027,
                            18.913834000000005,
                            0
                        ],
                        [
                            99.085025,
                            18.913868,
                            0
                        ],
                        [
                            99.084954,
                            18.914999,
                            0
                        ],
                        [
                            99.084878,
                            18.916224,
                            0
                        ],
                        [
                            99.084497,
                            18.919596000000002,
                            0
                        ],
                        [
                            99.084322,
                            18.920978000000005,
                            0
                        ],
                        [
                            99.08426,
                            18.921471,
                            0
                        ],
                        [
                            99.084249,
                            18.921559000000002,
                            0
                        ],
                        [
                            99.0841,
                            18.923506,
                            0
                        ],
                        [
                            99.084584,
                            18.926655999999998,
                            0
                        ],
                        [
                            99.085084,
                            18.927653,
                            0
                        ],
                        [
                            99.085001,
                            18.928081,
                            0
                        ],
                        [
                            99.08194,
                            18.927797,
                            0
                        ],
                        [
                            99.082339,
                            18.927385,
                            0
                        ],
                        [
                            99.08217200000001,
                            18.926721,
                            0
                        ],
                        [
                            99.082105,
                            18.926325000000002,
                            0
                        ],
                        [
                            99.082122,
                            18.925913,
                            0
                        ],
                        [
                            99.082138,
                            18.925438,
                            0
                        ],
                        [
                            99.082055,
                            18.925074000000002,
                            0
                        ],
                        [
                            99.081755,
                            18.924742,
                            0
                        ],
                        [
                            99.081422,
                            18.924441000000005,
                            0
                        ],
                        [
                            99.081056,
                            18.924282999999996,
                            0
                        ],
                        [
                            99.080341,
                            18.923951,
                            0
                        ],
                        [
                            99.079659,
                            18.924047,
                            0
                        ],
                        [
                            99.079376,
                            18.924062,
                            0
                        ],
                        [
                            99.078977,
                            18.923983,
                            0
                        ],
                        [
                            99.07852800000002,
                            18.923762,
                            0
                        ],
                        [
                            99.078079,
                            18.923636,
                            0
                        ],
                        [
                            99.077796,
                            18.923556999999995,
                            0
                        ],
                        [
                            99.07753,
                            18.923778,
                            0
                        ],
                        [
                            99.07733,
                            18.924095,
                            0
                        ],
                        [
                            99.077164,
                            18.924412,
                            0
                        ],
                        [
                            99.07701500000002,
                            18.924807,
                            0
                        ],
                        [
                            99.076799,
                            18.925013,
                            0
                        ],
                        [
                            99.07625,
                            18.925250999999996,
                            0
                        ],
                        [
                            99.075368,
                            18.925441,
                            0
                        ],
                        [
                            99.07490200000001,
                            18.925442,
                            0
                        ],
                        [
                            99.074769,
                            18.925283000000004,
                            0
                        ],
                        [
                            99.074769,
                            18.924713,
                            0
                        ],
                        [
                            99.074769,
                            18.924349000000003,
                            0
                        ],
                        [
                            99.074735,
                            18.924033,
                            0
                        ],
                        [
                            99.074336,
                            18.923827,
                            0
                        ],
                        [
                            99.073704,
                            18.923685,
                            0
                        ],
                        [
                            99.073072,
                            18.923495,
                            0
                        ],
                        [
                            99.072323,
                            18.923242,
                            0
                        ],
                        [
                            99.071575,
                            18.923068,
                            0
                        ],
                        [
                            99.070926,
                            18.922926,
                            0
                        ],
                        [
                            99.070543,
                            18.922926,
                            0
                        ],
                        [
                            99.070078,
                            18.923021,
                            0
                        ],
                        [
                            99.069512,
                            18.923101,
                            0
                        ],
                        [
                            99.068996,
                            18.922832,
                            0
                        ],
                        [
                            99.068547,
                            18.922721,
                            0
                        ],
                        [
                            99.067865,
                            18.922689999999996,
                            0
                        ],
                        [
                            99.067117,
                            18.922689999999996,
                            0
                        ],
                        [
                            99.066551,
                            18.922675,
                            0
                        ],
                        [
                            99.066069,
                            18.922738,
                            0
                        ],
                        [
                            99.06567,
                            18.922865000000005,
                            0
                        ],
                        [
                            99.06532,
                            18.923134000000005,
                            0
                        ],
                        [
                            99.065038,
                            18.922802,
                            0
                        ],
                        [
                            99.064738,
                            18.92258,
                            0
                        ],
                        [
                            99.064538,
                            18.922184,
                            0
                        ]
                    ]
                ]
            },
            "properties": {
                "name": "โครงการอ่างเก็บน้ำห้วยเกี๋ยง",
                "description": "PROJNAME: โครงการฯอ่างเก็บน้ำห้วยเกี๋ยง<br> OWNER: สำนักชลประทานที่ 1/โครงการชลประทานเชียงใหม่<br> RIDCODE: 01<br> PROJTYPE: 02<br> PROVNAME: เชียงใหม่<br> AMPHOE: สันทราย<br> TAMBON: หนองแหย่ง<br> VILLAGE: แม่ฮักพัฒนาเฉลิมพระเกียรติ<br> UTM_E: 508700<br> UTM_N: 2092800<br> UTMZONE: 47<br> MAPSHEET: 4846 IV<br> PRJAREAP: 0<br> IRRAREAP: 0<br> USEAREAP: 0<br> PROJAREA: 1196.74<br> IRRAREA: 509.51<br> A1AREA: 14.2<br> A2AREA: 29.64<br> A3AREA: 445.49<br> A7AREA: 20.18<br> A9AREA: 0<br> FRAREA: 106.99<br> WTAREA: 18.93<br> MLAREA: 449.51<br> UBAREA: 111.81<br> UIAREA: 0<br> CNAREA: 0<br> RDAREA: 0<br> LUYEAR: 2553<br> REMARK: ถ่ายโอน 28 ก.พ.2546 พิกัดเดิม ในโครงการ<br> PROJCODE: 01500102020019"
            }
        }
    ]
}