{
    "type": "FeatureCollection",
    "features": [
        {
            "type": "Feature",
            "geometry": {
                "type": "Polygon",
                "coordinates": [
                    [
                        [
                            99.18990521297464,
                            19.42504594049015,
                            0
                        ],
                        [
                            99.189458,
                            19.42428,
                            0
                        ],
                        [
                            99.189449,
                            19.424264,
                            0
                        ],
                        [
                            99.189445,
                            19.424256,
                            0
                        ],
                        [
                            99.18990521297464,
                            19.423771267603946,
                            0
                        ],
                        [
                            99.189933,
                            19.423742,
                            0
                        ],
                        [
                            99.19000900000002,
                            19.423663,
                            0
                        ],
                        [
                            99.189989,
                            19.423646999999995,
                            0
                        ],
                        [
                            99.18990521297464,
                            19.423580161691913,
                            0
                        ],
                        [
                            99.189287,
                            19.423087000000002,
                            0
                        ],
                        [
                            99.188979,
                            19.422841000000002,
                            0
                        ],
                        [
                            99.187042,
                            19.421122,
                            0
                        ],
                        [
                            99.187003,
                            19.421037,
                            0
                        ],
                        [
                            99.186638,
                            19.42023,
                            0
                        ],
                        [
                            99.186557,
                            19.420051,
                            0
                        ],
                        [
                            99.185407,
                            19.419842,
                            0
                        ],
                        [
                            99.185266,
                            19.419478,
                            0
                        ],
                        [
                            99.185225,
                            19.419455,
                            0
                        ],
                        [
                            99.185183,
                            19.41943,
                            0
                        ],
                        [
                            99.184935,
                            19.419286000000003,
                            0
                        ],
                        [
                            99.184217,
                            19.418867,
                            0
                        ],
                        [
                            99.183732,
                            19.418753,
                            0
                        ],
                        [
                            99.18345,
                            19.418792,
                            0
                        ],
                        [
                            99.182724,
                            19.418295,
                            0
                        ],
                        [
                            99.182111,
                            19.418387,
                            0
                        ],
                        [
                            99.181245,
                            19.418518,
                            0
                        ],
                        [
                            99.181192,
                            19.418526,
                            0
                        ],
                        [
                            99.181312,
                            19.418124000000002,
                            0
                        ],
                        [
                            99.181143,
                            19.417832,
                            0
                        ],
                        [
                            99.180969,
                            19.417532,
                            0
                        ],
                        [
                            99.180942,
                            19.417460000000002,
                            0
                        ],
                        [
                            99.180382,
                            19.415965999999997,
                            0
                        ],
                        [
                            99.18018000000001,
                            19.415428,
                            0
                        ],
                        [
                            99.180481,
                            19.415258999999995,
                            0
                        ],
                        [
                            99.180624,
                            19.415179,
                            0
                        ],
                        [
                            99.181119,
                            19.414582000000003,
                            0
                        ],
                        [
                            99.181147,
                            19.414547,
                            0
                        ],
                        [
                            99.18104600000001,
                            19.414375000000003,
                            0
                        ],
                        [
                            99.182779,
                            19.413647,
                            0
                        ],
                        [
                            99.180841,
                            19.411410000000004,
                            0
                        ],
                        [
                            99.18372200000002,
                            19.409629,
                            0
                        ],
                        [
                            99.184146,
                            19.410221,
                            0
                        ],
                        [
                            99.185617,
                            19.40934,
                            0
                        ],
                        [
                            99.185072,
                            19.408728,
                            0
                        ],
                        [
                            99.185152,
                            19.408326000000002,
                            0
                        ],
                        [
                            99.184243,
                            19.406662999999998,
                            0
                        ],
                        [
                            99.184202,
                            19.406089,
                            0
                        ],
                        [
                            99.184113,
                            19.405914,
                            0
                        ],
                        [
                            99.184064,
                            19.405819,
                            0
                        ],
                        [
                            99.183987,
                            19.405667,
                            0
                        ],
                        [
                            99.183919,
                            19.405535,
                            0
                        ],
                        [
                            99.184769,
                            19.40436,
                            0
                        ],
                        [
                            99.184805,
                            19.404310000000002,
                            0
                        ],
                        [
                            99.185329,
                            19.404289999999996,
                            0
                        ],
                        [
                            99.185381,
                            19.404312000000004,
                            0
                        ],
                        [
                            99.186136,
                            19.404634,
                            0
                        ],
                        [
                            99.187789,
                            19.404421,
                            0
                        ],
                        [
                            99.189563,
                            19.404343000000004,
                            0
                        ],
                        [
                            99.18990521297464,
                            19.404515433339288,
                            0
                        ],
                        [
                            99.190208,
                            19.404668000000004,
                            0
                        ],
                        [
                            99.19144000000001,
                            19.40633,
                            0
                        ],
                        [
                            99.19195800000001,
                            19.40615,
                            0
                        ],
                        [
                            99.192266,
                            19.406043,
                            0
                        ],
                        [
                            99.192851,
                            19.406176,
                            0
                        ],
                        [
                            99.193054,
                            19.407496000000002,
                            0
                        ],
                        [
                            99.193753,
                            19.407311,
                            0
                        ],
                        [
                            99.194753,
                            19.407048000000003,
                            0
                        ],
                        [
                            99.19494900000001,
                            19.406996,
                            0
                        ],
                        [
                            99.195232,
                            19.408105,
                            0
                        ],
                        [
                            99.196643,
                            19.407855,
                            0
                        ],
                        [
                            99.1968,
                            19.407499,
                            0
                        ],
                        [
                            99.197226,
                            19.406535,
                            0
                        ],
                        [
                            99.197576,
                            19.405587,
                            0
                        ],
                        [
                            99.197774,
                            19.405399000000003,
                            0
                        ],
                        [
                            99.198017,
                            19.405110000000004,
                            0
                        ],
                        [
                            99.198235,
                            19.404705,
                            0
                        ],
                        [
                            99.198747,
                            19.403639,
                            0
                        ],
                        [
                            99.19889400000001,
                            19.403275,
                            0
                        ],
                        [
                            99.198952,
                            19.40307,
                            0
                        ],
                        [
                            99.199048,
                            19.402866,
                            0
                        ],
                        [
                            99.199061,
                            19.402839,
                            0
                        ],
                        [
                            99.199096,
                            19.402764,
                            0
                        ],
                        [
                            99.199103,
                            19.402491,
                            0
                        ],
                        [
                            99.19910500000002,
                            19.402421,
                            0
                        ],
                        [
                            99.199173,
                            19.399531,
                            0
                        ],
                        [
                            99.198909,
                            19.397848,
                            0
                        ],
                        [
                            99.199536,
                            19.395346,
                            0
                        ],
                        [
                            99.199789,
                            19.395016,
                            0
                        ],
                        [
                            99.200059,
                            19.394660000000002,
                            0
                        ],
                        [
                            99.200293,
                            19.39428,
                            0
                        ],
                        [
                            99.200441,
                            19.394032000000003,
                            0
                        ],
                        [
                            99.20062600000001,
                            19.393659,
                            0
                        ],
                        [
                            99.200654,
                            19.393616,
                            0
                        ],
                        [
                            99.200678,
                            19.393581,
                            0
                        ],
                        [
                            99.200709,
                            19.393531,
                            0
                        ],
                        [
                            99.200849,
                            19.393454,
                            0
                        ],
                        [
                            99.201188,
                            19.393082000000003,
                            0
                        ],
                        [
                            99.201397,
                            19.392594,
                            0
                        ],
                        [
                            99.201604,
                            19.392081,
                            0
                        ],
                        [
                            99.20162300000001,
                            19.392049000000004,
                            0
                        ],
                        [
                            99.201672,
                            19.391567,
                            0
                        ],
                        [
                            99.201693,
                            19.391352,
                            0
                        ],
                        [
                            99.2017,
                            19.391347,
                            0
                        ],
                        [
                            99.201743,
                            19.391074000000003,
                            0
                        ],
                        [
                            99.201951,
                            19.390802000000004,
                            0
                        ],
                        [
                            99.202264,
                            19.390372,
                            0
                        ],
                        [
                            99.202394,
                            19.390017,
                            0
                        ],
                        [
                            99.202803,
                            19.389620000000004,
                            0
                        ],
                        [
                            99.20335,
                            19.389107000000003,
                            0
                        ],
                        [
                            99.203416,
                            19.388964,
                            0
                        ],
                        [
                            99.203434,
                            19.388948,
                            0
                        ],
                        [
                            99.203514,
                            19.388745000000004,
                            0
                        ],
                        [
                            99.203787,
                            19.388046999999997,
                            0
                        ],
                        [
                            99.204298,
                            19.386743,
                            0
                        ],
                        [
                            99.204439,
                            19.386384000000003,
                            0
                        ],
                        [
                            99.204759,
                            19.385006,
                            0
                        ],
                        [
                            99.204838,
                            19.383476,
                            0
                        ],
                        [
                            99.20503600000002,
                            19.380970000000005,
                            0
                        ],
                        [
                            99.20508300000002,
                            19.381,
                            0
                        ],
                        [
                            99.205555,
                            19.381305,
                            0
                        ],
                        [
                            99.206132,
                            19.381677999999997,
                            0
                        ],
                        [
                            99.206244,
                            19.381749,
                            0
                        ],
                        [
                            99.206349,
                            19.381817000000005,
                            0
                        ],
                        [
                            99.206751,
                            19.382077,
                            0
                        ],
                        [
                            99.207146,
                            19.382169,
                            0
                        ],
                        [
                            99.207236,
                            19.38219,
                            0
                        ],
                        [
                            99.208223,
                            19.382420000000003,
                            0
                        ],
                        [
                            99.208537,
                            19.382420000000003,
                            0
                        ],
                        [
                            99.208714,
                            19.382419,
                            0
                        ],
                        [
                            99.20907700000001,
                            19.382419,
                            0
                        ],
                        [
                            99.209258,
                            19.382419000000002,
                            0
                        ],
                        [
                            99.209715,
                            19.382418,
                            0
                        ],
                        [
                            99.21041600000001,
                            19.383184,
                            0
                        ],
                        [
                            99.210612,
                            19.383397999999996,
                            0
                        ],
                        [
                            99.210983,
                            19.383803000000004,
                            0
                        ],
                        [
                            99.21113,
                            19.383964,
                            0
                        ],
                        [
                            99.211807,
                            19.384704,
                            0
                        ],
                        [
                            99.212077,
                            19.384998,
                            0
                        ],
                        [
                            99.21211,
                            19.385002,
                            0
                        ],
                        [
                            99.213137,
                            19.385112,
                            0
                        ],
                        [
                            99.213449,
                            19.385146,
                            0
                        ],
                        [
                            99.214693,
                            19.38528,
                            0
                        ],
                        [
                            99.215206,
                            19.385336,
                            0
                        ],
                        [
                            99.215584,
                            19.385376,
                            0
                        ],
                        [
                            99.216718,
                            19.385391,
                            0
                        ],
                        [
                            99.21695500000001,
                            19.385394,
                            0
                        ],
                        [
                            99.217067,
                            19.38555,
                            0
                        ],
                        [
                            99.217339,
                            19.385929,
                            0
                        ],
                        [
                            99.218286,
                            19.385832,
                            0
                        ],
                        [
                            99.21865000000001,
                            19.386195000000004,
                            0
                        ],
                        [
                            99.218408,
                            19.386425,
                            0
                        ],
                        [
                            99.217763,
                            19.386522,
                            0
                        ],
                        [
                            99.217824,
                            19.386808,
                            0
                        ],
                        [
                            99.217973,
                            19.386888,
                            0
                        ],
                        [
                            99.21825,
                            19.387037000000003,
                            0
                        ],
                        [
                            99.21857,
                            19.387209000000002,
                            0
                        ],
                        [
                            99.21982100000001,
                            19.388259999999995,
                            0
                        ],
                        [
                            99.22029000000002,
                            19.388515,
                            0
                        ],
                        [
                            99.221012,
                            19.388909,
                            0
                        ],
                        [
                            99.220629,
                            19.389541,
                            0
                        ],
                        [
                            99.22051,
                            19.390268,
                            0
                        ],
                        [
                            99.221317,
                            19.390802000000004,
                            0
                        ],
                        [
                            99.222184,
                            19.390992,
                            0
                        ],
                        [
                            99.22219200000002,
                            19.391026999999998,
                            0
                        ],
                        [
                            99.222609,
                            19.392637,
                            0
                        ],
                        [
                            99.222913,
                            19.393593,
                            0
                        ],
                        [
                            99.223075,
                            19.394568,
                            0
                        ],
                        [
                            99.223076,
                            19.395164000000005,
                            0
                        ],
                        [
                            99.223077,
                            19.395506,
                            0
                        ],
                        [
                            99.223622,
                            19.396481,
                            0
                        ],
                        [
                            99.223785,
                            19.396794000000003,
                            0
                        ],
                        [
                            99.224087,
                            19.397379,
                            0
                        ],
                        [
                            99.223765,
                            19.3978,
                            0
                        ],
                        [
                            99.22388700000002,
                            19.398699,
                            0
                        ],
                        [
                            99.22405,
                            19.399369,
                            0
                        ],
                        [
                            99.224433,
                            19.399712,
                            0
                        ],
                        [
                            99.224354,
                            19.400439,
                            0
                        ],
                        [
                            99.224515,
                            19.400629999999996,
                            0
                        ],
                        [
                            99.224314,
                            19.401109,
                            0
                        ],
                        [
                            99.224819,
                            19.401414,
                            0
                        ],
                        [
                            99.225231,
                            19.40253,
                            0
                        ],
                        [
                            99.225264,
                            19.402619,
                            0
                        ],
                        [
                            99.226171,
                            19.402867000000004,
                            0
                        ],
                        [
                            99.226294,
                            19.403225000000003,
                            0
                        ],
                        [
                            99.226414,
                            19.403574,
                            0
                        ],
                        [
                            99.227,
                            19.404396,
                            0
                        ],
                        [
                            99.227142,
                            19.405046,
                            0
                        ],
                        [
                            99.226699,
                            19.405831,
                            0
                        ],
                        [
                            99.22692300000001,
                            19.407036,
                            0
                        ],
                        [
                            99.227105,
                            19.407322,
                            0
                        ],
                        [
                            99.225392,
                            19.407707,
                            0
                        ],
                        [
                            99.223095,
                            19.408762,
                            0
                        ],
                        [
                            99.223136,
                            19.409278,
                            0
                        ],
                        [
                            99.222079,
                            19.409596,
                            0
                        ],
                        [
                            99.221987,
                            19.409623999999997,
                            0
                        ],
                        [
                            99.22201800000002,
                            19.409712000000003,
                            0
                        ],
                        [
                            99.222432,
                            19.410886,
                            0
                        ],
                        [
                            99.222453,
                            19.411498,
                            0
                        ],
                        [
                            99.22302,
                            19.412856000000005,
                            0
                        ],
                        [
                            99.223101,
                            19.41364,
                            0
                        ],
                        [
                            99.222275,
                            19.413851,
                            0
                        ],
                        [
                            99.22145500000002,
                            19.413814,
                            0
                        ],
                        [
                            99.221448,
                            19.413814,
                            0
                        ],
                        [
                            99.221036,
                            19.413970999999997,
                            0
                        ],
                        [
                            99.22064200000001,
                            19.414120999999998,
                            0
                        ],
                        [
                            99.221206,
                            19.415086000000002,
                            0
                        ],
                        [
                            99.22139,
                            19.415402,
                            0
                        ],
                        [
                            99.221616,
                            19.416466,
                            0
                        ],
                        [
                            99.221674,
                            19.416740000000004,
                            0
                        ],
                        [
                            99.22224,
                            19.417811,
                            0
                        ],
                        [
                            99.222227,
                            19.417993999999997,
                            0
                        ],
                        [
                            99.222181,
                            19.418634,
                            0
                        ],
                        [
                            99.222324,
                            19.420145,
                            0
                        ],
                        [
                            99.22287,
                            19.421674,
                            0
                        ],
                        [
                            99.223158,
                            19.421925,
                            0
                        ],
                        [
                            99.223658,
                            19.422361999999996,
                            0
                        ],
                        [
                            99.223681,
                            19.422421999999997,
                            0
                        ],
                        [
                            99.223789,
                            19.422697,
                            0
                        ],
                        [
                            99.22379900000001,
                            19.422725,
                            0
                        ],
                        [
                            99.224465,
                            19.423164,
                            0
                        ],
                        [
                            99.224732,
                            19.423978,
                            0
                        ],
                        [
                            99.224815,
                            19.424233,
                            0
                        ],
                        [
                            99.224891,
                            19.424465,
                            0
                        ],
                        [
                            99.224896,
                            19.424473000000003,
                            0
                        ],
                        [
                            99.225515,
                            19.425425,
                            0
                        ],
                        [
                            99.22586,
                            19.425955,
                            0
                        ],
                        [
                            99.226469,
                            19.426497000000005,
                            0
                        ],
                        [
                            99.227576,
                            19.427484,
                            0
                        ],
                        [
                            99.228142,
                            19.428573,
                            0
                        ],
                        [
                            99.229051,
                            19.429508999999996,
                            0
                        ],
                        [
                            99.22938800000001,
                            19.430172999999996,
                            0
                        ],
                        [
                            99.230001,
                            19.431383,
                            0
                        ],
                        [
                            99.23085,
                            19.432797,
                            0
                        ],
                        [
                            99.227262,
                            19.433663,
                            0
                        ],
                        [
                            99.226818,
                            19.433394999999997,
                            0
                        ],
                        [
                            99.226093,
                            19.433587,
                            0
                        ],
                        [
                            99.225508,
                            19.433531,
                            0
                        ],
                        [
                            99.225125,
                            19.43399,
                            0
                        ],
                        [
                            99.224783,
                            19.434182,
                            0
                        ],
                        [
                            99.22452,
                            19.433953,
                            0
                        ],
                        [
                            99.224503,
                            19.433585000000004,
                            0
                        ],
                        [
                            99.2245,
                            19.433513000000005,
                            0
                        ],
                        [
                            99.223738,
                            19.43302,
                            0
                        ],
                        [
                            99.223733,
                            19.433017,
                            0
                        ],
                        [
                            99.223186,
                            19.432869,
                            0
                        ],
                        [
                            99.223025,
                            19.432826,
                            0
                        ],
                        [
                            99.222886,
                            19.432788,
                            0
                        ],
                        [
                            99.22269,
                            19.432788,
                            0
                        ],
                        [
                            99.222523,
                            19.432788,
                            0
                        ],
                        [
                            99.221384,
                            19.432483000000005,
                            0
                        ],
                        [
                            99.221154,
                            19.432421999999995,
                            0
                        ],
                        [
                            99.220889,
                            19.432351,
                            0
                        ],
                        [
                            99.220729,
                            19.432379,
                            0
                        ],
                        [
                            99.220316,
                            19.432451,
                            0
                        ],
                        [
                            99.220123,
                            19.432485,
                            0
                        ],
                        [
                            99.22007900000001,
                            19.432587,
                            0
                        ],
                        [
                            99.219761,
                            19.433327,
                            0
                        ],
                        [
                            99.219319,
                            19.434514,
                            0
                        ],
                        [
                            99.219281,
                            19.434502,
                            0
                        ],
                        [
                            99.21747900000001,
                            19.433923,
                            0
                        ],
                        [
                            99.216293,
                            19.433542000000003,
                            0
                        ],
                        [
                            99.216247,
                            19.433186,
                            0
                        ],
                        [
                            99.216191,
                            19.432758,
                            0
                        ],
                        [
                            99.216107,
                            19.432630999999997,
                            0
                        ],
                        [
                            99.21605000000001,
                            19.432546000000002,
                            0
                        ],
                        [
                            99.215867,
                            19.432268999999998,
                            0
                        ],
                        [
                            99.21574700000001,
                            19.432089,
                            0
                        ],
                        [
                            99.21561400000002,
                            19.432041,
                            0
                        ],
                        [
                            99.2149,
                            19.431784000000004,
                            0
                        ],
                        [
                            99.21433,
                            19.431655,
                            0
                        ],
                        [
                            99.213044,
                            19.431365,
                            0
                        ],
                        [
                            99.213102,
                            19.43226,
                            0
                        ],
                        [
                            99.21310600000001,
                            19.432321999999996,
                            0
                        ],
                        [
                            99.21243,
                            19.432515000000002,
                            0
                        ],
                        [
                            99.2123,
                            19.432552,
                            0
                        ],
                        [
                            99.2123,
                            19.432556,
                            0
                        ],
                        [
                            99.21232000000002,
                            19.432915,
                            0
                        ],
                        [
                            99.211252,
                            19.433051,
                            0
                        ],
                        [
                            99.210576,
                            19.433185999999996,
                            0
                        ],
                        [
                            99.210486,
                            19.433205000000005,
                            0
                        ],
                        [
                            99.210485,
                            19.433211,
                            0
                        ],
                        [
                            99.21045900000001,
                            19.43401,
                            0
                        ],
                        [
                            99.210439,
                            19.434635,
                            0
                        ],
                        [
                            99.210409,
                            19.435547999999997,
                            0
                        ],
                        [
                            99.210408,
                            19.435577,
                            0
                        ],
                        [
                            99.208614,
                            19.435673999999995,
                            0
                        ],
                        [
                            99.208585,
                            19.435607,
                            0
                        ],
                        [
                            99.207582,
                            19.433226999999995,
                            0
                        ],
                        [
                            99.207318,
                            19.431907,
                            0
                        ],
                        [
                            99.205889,
                            19.432349000000002,
                            0
                        ],
                        [
                            99.205827,
                            19.432368,
                            0
                        ],
                        [
                            99.20535,
                            19.432062,
                            0
                        ],
                        [
                            99.205322,
                            19.432044000000005,
                            0
                        ],
                        [
                            99.205291,
                            19.432058999999995,
                            0
                        ],
                        [
                            99.20443600000002,
                            19.432465000000004,
                            0
                        ],
                        [
                            99.204431,
                            19.432460000000003,
                            0
                        ],
                        [
                            99.204072,
                            19.431957,
                            0
                        ],
                        [
                            99.204011,
                            19.431873,
                            0
                        ],
                        [
                            99.203184,
                            19.431490999999998,
                            0
                        ],
                        [
                            99.20309300000001,
                            19.431481,
                            0
                        ],
                        [
                            99.203024,
                            19.431473,
                            0
                        ],
                        [
                            99.20268,
                            19.431434,
                            0
                        ],
                        [
                            99.202357,
                            19.431129,
                            0
                        ],
                        [
                            99.202373,
                            19.431073000000005,
                            0
                        ],
                        [
                            99.20270400000001,
                            19.429897000000004,
                            0
                        ],
                        [
                            99.202718,
                            19.429847,
                            0
                        ],
                        [
                            99.202423,
                            19.429853000000005,
                            0
                        ],
                        [
                            99.202006,
                            19.429863000000005,
                            0
                        ],
                        [
                            99.201831,
                            19.429866999999998,
                            0
                        ],
                        [
                            99.20179,
                            19.429867999999995,
                            0
                        ],
                        [
                            99.200916,
                            19.429883000000004,
                            0
                        ],
                        [
                            99.200721,
                            19.429887000000004,
                            0
                        ],
                        [
                            99.200682,
                            19.429887,
                            0
                        ],
                        [
                            99.200086,
                            19.43009,
                            0
                        ],
                        [
                            99.199271,
                            19.430367000000004,
                            0
                        ],
                        [
                            99.199079,
                            19.430543,
                            0
                        ],
                        [
                            99.198768,
                            19.430827000000004,
                            0
                        ],
                        [
                            99.19763,
                            19.4316,
                            0
                        ],
                        [
                            99.197357,
                            19.431785,
                            0
                        ],
                        [
                            99.196872,
                            19.430771,
                            0
                        ],
                        [
                            99.19656,
                            19.430857,
                            0
                        ],
                        [
                            99.195999,
                            19.431011000000005,
                            0
                        ],
                        [
                            99.195412,
                            19.431171,
                            0
                        ],
                        [
                            99.195401,
                            19.431175,
                            0
                        ],
                        [
                            99.194896,
                            19.430104,
                            0
                        ],
                        [
                            99.194553,
                            19.430219,
                            0
                        ],
                        [
                            99.19451500000001,
                            19.430172000000002,
                            0
                        ],
                        [
                            99.193543,
                            19.428958,
                            0
                        ],
                        [
                            99.193527,
                            19.428932,
                            0
                        ],
                        [
                            99.19213200000002,
                            19.426646999999996,
                            0
                        ],
                        [
                            99.19204800000001,
                            19.426511,
                            0
                        ],
                        [
                            99.191114,
                            19.426741000000003,
                            0
                        ],
                        [
                            99.19087900000001,
                            19.426799000000003,
                            0
                        ],
                        [
                            99.190686,
                            19.425902,
                            0
                        ],
                        [
                            99.190616,
                            19.425575000000002,
                            0
                        ],
                        [
                            99.190192,
                            19.425537,
                            0
                        ],
                        [
                            99.190175,
                            19.425508,
                            0
                        ],
                        [
                            99.18990521297464,
                            19.42504594049015,
                            0
                        ]
                    ]
                ]
            },
            "properties": {
                "name": "",
                "description": "PROJNAME: <br> OWNER:  1/<br> RIDCODE: 01<br> PROJTYPE: 02<br> PROVNAME: <br> AMPHOE: <br> TAMBON: <br> VILLAGE: <br> UTM_E: 524435<br> UTM_N: 2148461<br> UTMZONE: 47<br> MAPSHEET: 4847IV<br> PRJAREAP: 0<br> IRRAREAP: 0<br> USEAREAP: 0<br> PROJAREA: 10816.59<br> IRRAREA: 9162.4<br> A1AREA: 8067.08<br> A2AREA: 0<br> A3AREA: 1077.25<br> A7AREA: 18.07<br> A9AREA: 0<br> FRAREA: 14.18<br> WTAREA: 15.76<br> MLAREA: 302.97<br> UBAREA: 1316.06<br> UIAREA: 5.22<br> CNAREA: 0<br> RDAREA: 0<br> LUYEAR: 2553<br> REMARK: <br> PROJCODE: 01500102020008"
            }
        }
    ]
}